denrey_neural_network-0.1.3.dist-info/licenses/LICENSE
neuralnetwork/__init__.py
neuralnetwork/activation_functions.py
neuralnetwork/activation_layer.py
neuralnetwork/fully_connected_layer.py
neuralnetwork/layer.py
neuralnetwork/loss_functions.py
neuralnetwork/neural_network.py
neuralnetwork/py.typed
denrey_neural_network-0.1.3.dist-info/METADATA
denrey_neural_network-0.1.3.dist-info/WHEEL
denrey_neural_network-0.1.3.dist-info/top_level.txt
denrey_neural_network-0.1.3.dist-info/RECORD
