Metadata-Version: 2.4
Name: denrey_neural_network
Version: 0.1.3
Summary: A simple Neural Network library.
Author-email: Denrey Christy <denreyc@gmail.com>
Requires-Python: >=3.8
License-File: LICENSE
Requires-Dist: numpy
Dynamic: license-file
